CHANGELOG
LICENSE
MANIFEST.in
README.rst
TODO
setup.py
django_infopush.egg-info/PKG-INFO
django_infopush.egg-info/SOURCES.txt
django_infopush.egg-info/dependency_links.txt
django_infopush.egg-info/requires.txt
django_infopush.egg-info/top_level.txt
docs/MYSQL.rst
docs/SETTINGS.rst
docs/img/push_admin_add.png
docs/img/push_admin_add_thumb.png
docs/img/push_admin_list.png
docs/img/push_admin_list_thumb.png
push/__init__.py
push/admin.py
push/apps.py
push/filters.py
push/forms.py
push/models.py
push/settings.py
push/tests.py
push/urls.py
push/views.py
push/locale/ru/LC_MESSAGES/django.mo
push/locale/ru/LC_MESSAGES/django.po
push/management/__init__.py
push/management/commands/__init__.py
push/management/commands/pushsend.py
push/migrations/0001_initial.py
push/migrations/0002_auto_20190408_1636.py
push/migrations/0003_auto_20200707_1439.py
push/migrations/0004_auto_20221006_1553.py
push/migrations/__init__.py
push/static/push/img/app_icon.png
push/static/push/img/chrome_android_disable_1.png
push/static/push/img/chrome_android_disable_2.png
push/static/push/img/chrome_android_disable_3.png
push/static/push/img/chrome_disable.png
push/static/push/img/ff_disable.png
push/static/push/img/icon.png
push/static/push/js/jstz.min.js
push/static/push/js/push.js
push/templates/admin/push/change_list.html
push/templates/push/_head_include.html
push/templates/push/_info_disable_title.html
push/templates/push/_info_disable_txt.html
push/templates/push/_on_off_title.html
push/templates/push/_on_off_txt.html
push/templates/push/info_disable.html
push/templates/push/on_off.html
push/templates/push/service-worker.js
push/templatetags/__init__.py
push/templatetags/push_settings.py