Metadata-Version: 2.1
Name: django-infopush
Version: 1.8.1
Summary: Django reusable app, what allows to send web push.
Home-page: https://github.com/kilgoretrout1985/django_infopush
Author: Yuriy Zemskov
Author-email: zemskyura@gmail.com
License: MIT
Keywords: push webpush notifications fcm gcm vapid django reusable application app
Platform: UNKNOWN
Classifier: Environment :: Web Environment
Classifier: Framework :: Django
Classifier: Framework :: Django :: 3.2
Classifier: Framework :: Django :: 4.0
Classifier: Framework :: Django :: 4.1
Classifier: Intended Audience :: Developers
Classifier: Operating System :: OS Independent
Classifier: Programming Language :: Python
Classifier: Programming Language :: Python :: 3
Classifier: Programming Language :: Python :: 3.7
Classifier: Programming Language :: Python :: 3.8
Classifier: Programming Language :: Python :: 3.9
Classifier: Programming Language :: Python :: 3.10
Classifier: Topic :: Internet :: WWW/HTTP
Classifier: Topic :: Internet :: WWW/HTTP :: Dynamic Content
